{
  "sort_order": 6,
  "title": "Free Audio Fitness Classes with Aaptiv",
  "seo_title": "Free Audio Fitness Classes with Aaptiv",
  "url_friendly_name": "aaptiv-guided-fitness-training",
  "image": {
    "name": "aaptiv-new",
    "file_name": "aaptiv-new.jpg",
    "url": "//cdn.traveltripper.io/site-assets/192_368_23229/media/2019-02-01-021133/aaptiv-new.jpg",
    "tags": "",
    "description": "",
    "date_added": "2019-02-01-021133",
    "file_type": "image/jpeg",
    "width": 2000,
    "height": 1333,
    "file_size": 222571,
    "url_large": "//cdn.traveltripper.io/site-assets/192_368_23229/media/2019-02-01-021133/large_aaptiv-new.jpg",
    "url_medium": "//cdn.traveltripper.io/site-assets/192_368_23229/media/2019-02-01-021133/medium_aaptiv-new.jpg",
    "url_small": "//cdn.traveltripper.io/site-assets/192_368_23229/media/2019-02-01-021133/small_aaptiv-new.jpg",
    "url_xsmall": "//cdn.traveltripper.io/site-assets/192_368_23229/media/2019-02-01-021133/xsmall_aaptiv-new.jpg",
    "url_thumb": "//cdn.traveltripper.io/site-assets/192_368_23229/media/2019-02-01-021133/thumb_aaptiv-new.jpg",
    "path": "//cdn.traveltripper.io/site-assets/192_368_23229/media/2019-02-01-021133/aaptiv-new.jpg",
    "alt": "Aaptiv",
    "caption": ""
  },
  "seo_description": "Stay fit and feel your best during your stay with fitness classes led by expert personal trainers. ",
  "contents": "<p id=\"mf79\">Stay fit and feel your best during your stay with fitness classes led by expert personal trainers. Aaptiv gives you thousands of audio-guided workouts for treadmill, cardio machines, running, strength training, yoga, meditation and more &mdash; all set to inspiring music by today&rsquo;s top artists. It&rsquo;s like having a personal trainer whenever and wherever you want one &ndash; all for <strong>free while you&rsquo;re in residence.</strong> Get complimentary, unlimited access during your stay through the Aaptiv smartphone app. To learn more visit <a title=\"Aaptiv\" href=\"https://aaptiv.com/\" target=\"_blank\" rel=\"noopener noreferrer\">Aaptiv.com</a> or stop by the Front Desk.</p>\n<p><a class=\"common-btn\" href=\"https://aaptiv.com/\" target=\"_blank\" rel=\"noopener noreferrer\">LEARN MORE</a></p>",
  "publish_title": false
}